pygrappa/pruno.py
pygrappa/grog_powers.cpython-310-x86_64-linux-gnu.so
pygrappa/gfactor.py
pygrappa/find_acs.py
pygrappa/seggrappa.py
pygrappa/tgrappa.py
pygrappa/igrappa.py
pygrappa/lustig_grappa.py
pygrappa/radialgrappaop.py
pygrappa/hpgrappa.py
pygrappa/sense1d.py
pygrappa/ncgrappa.py
pygrappa/kspa.py
pygrappa/slicegrappa.py
pygrappa/splitslicegrappa.py
pygrappa/cgrappa.cpython-310-x86_64-linux-gnu.so
pygrappa/kernels.py
pygrappa/nlgrappa.py
pygrappa/cgsense.py
pygrappa/run_tests.py
pygrappa/grappa.py
pygrappa/vcgrappa.py
pygrappa/coils.py
pygrappa/grappaop.py
pygrappa/pars.py
pygrappa/nlgrappa_matlab.py
pygrappa/ttgrappa.py
pygrappa/__init__.py
pygrappa/grog_gridding.cpython-310-x86_64-linux-gnu.so
pygrappa/mdgrappa.py
pygrappa/train_kernels.cpython-310-x86_64-linux-gnu.so
pygrappa/grog.py
pygrappa/benchmarks/benchmark.py
pygrappa/benchmarks/__init__.py
pygrappa/tests/test_grappa.py
pygrappa/tests/test_mdgrappa.py
pygrappa/tests/test_hpgrappa.py
pygrappa/tests/test_vcgrappa.py
pygrappa/tests/helpers.py
pygrappa/tests/test_cgrappa.py
pygrappa/tests/__init__.py
pygrappa/tests/test_cgsense.py
pygrappa/tests/test_igrappa.py
pygrappa/utils/gridder.py
pygrappa/utils/gaussian_csm.py
pygrappa/utils/disjoint_csm.py
pygrappa/utils/__init__.py
pygrappa/examples/basic_cgsense.py
pygrappa/examples/basic_splitslicegrappa.py
pygrappa/examples/md_cgsense.py
pygrappa/examples/basic_ttgrappa.py
pygrappa/examples/tikhonov_regularization.py
pygrappa/examples/primefac_grog.py
pygrappa/examples/basic_gridding.py
pygrappa/examples/basic_grappa.py
pygrappa/examples/bart_pars.py
pygrappa/examples/basic_gfactor.py
pygrappa/examples/basic_slicegrappa.py
pygrappa/examples/inverse_grog.py
pygrappa/examples/basic_seggrappa.py
pygrappa/examples/basic_tgrappa.py
pygrappa/examples/basic_vcgrappa.py
pygrappa/examples/basic_grappaop.py
pygrappa/examples/basic_nlgrappa_matlab.py
pygrappa/examples/__init__.py
pygrappa-0.26.3.dist-info/METADATA
pygrappa-0.26.3.dist-info/RECORD
pygrappa-0.26.3.dist-info/WHEEL
