Metadata-Version: 2.1
Name: pygrappa
Version: 0.26.3
Summary: GeneRalized Autocalibrating Partially Parallel Acquisitions.
Keywords: mri,grappa,sense
License: MIT
Classifier: Programming Language :: Python :: 3
Requires-Python: >=3.9
Provides-Extra: test
Provides-Extra: examples
Requires-Dist: pytest; extra == "test"
Requires-Dist: flake8; extra == "test"
Requires-Dist: phantominator; extra == "test"
Requires-Dist: matplotlib; extra == "examples"
Requires-Dist: sckikit-image; extra == "examples"
Requires-Dist: tqdm; extra == "examples"
Requires-Dist: phantominator; extra == "examples"
